datasette_gzip/__init__.py
datasette_gzip-0.2.dist-info/LICENSE
datasette_gzip-0.2.dist-info/METADATA
datasette_gzip-0.2.dist-info/WHEEL
datasette_gzip-0.2.dist-info/entry_points.txt
datasette_gzip-0.2.dist-info/top_level.txt
datasette_gzip-0.2.dist-info/RECORD
