Metadata-Version: 2.1
Name: datasette-gzip
Version: 0.2
Summary: Add gzip compression to Datasette
Home-page: https://github.com/simonw/datasette-gzip
Author: Simon Willison
License: Apache License, Version 2.0
Project-URL: Issues, https://github.com/simonw/datasette-gzip/issues
Project-URL: CI, https://github.com/simonw/datasette-gzip/actions
Project-URL: Changelog, https://github.com/simonw/datasette-gzip/releases
Platform: UNKNOWN
Classifier: Framework :: Datasette
Classifier: License :: OSI Approved :: Apache Software License
Requires-Python: >=3.7
License-File: LICENSE
Requires-Dist: datasette
Requires-Dist: asgi-gzip
Provides-Extra: test
Requires-Dist: pytest ; extra == 'test'
Requires-Dist: pytest-asyncio ; extra == 'test'
